soft_webauthn.py
soft_webauthn-0.1.4.dist-info/LICENSE
soft_webauthn-0.1.4.dist-info/METADATA
soft_webauthn-0.1.4.dist-info/WHEEL
soft_webauthn-0.1.4.dist-info/top_level.txt
soft_webauthn-0.1.4.dist-info/RECORD
