Metadata-Version: 2.1
Name: soft-webauthn
Version: 0.1.4
Summary: Python webauthn software authenticator
Home-page: https://github.com/bodik/soft-webauthn
Author: Radoslav Bodó
Author-email: bodik@cesnet.cz
License: UNKNOWN
Platform: UNKNOWN
Classifier: Programming Language :: Python :: 3
Classifier: License :: OSI Approved :: MIT License
